adscode/__init__.py
adscode/descriptive.py
adscode/imputation.py
adscode/outlier.py
adscode/performance.py
adscode/smote.py
adscode/timeseries.py
adscode/url.py
adscode/visualization.py
adscode-0.1.0.dist-info/METADATA
adscode-0.1.0.dist-info/WHEEL
adscode-0.1.0.dist-info/top_level.txt
adscode-0.1.0.dist-info/RECORD
